fifo/fifo.v
module fifo #(parameter DEPTH=8, DATA_WIDTH=16) (
  input clk, rst_n,
  input w_en, r_en,
  input [DATA_WIDTH-1:0] data_in,
  output reg [DATA_WIDTH-1:0] data_out,
  output full, empty
);
  
  reg [$clog2(DEPTH)-1:0] w_ptr, r_ptr;
  reg [DATA_WIDTH-1:0] fifo[DEPTH];
  
  // Set Default values on reset.
  always@(posedge clk) 
  begin
      if(!rst_n) 
      begin
          w_ptr <= 0; r_ptr <= 0;
          data_out <= 0;
      end
      else 
      begin

          // To read data from FIFO
          if(w_en & !full)begin
              fifo[w_ptr] <= data_in;
              w_ptr <= w_ptr + 1;
          end

          // To read data from FIFO
          if(r_en & !empty) begin
              data_out <= fifo[r_ptr];
              r_ptr <= r_ptr + 1;
          end
      end
  end

  assign full = ((w_ptr+1'b1) == r_ptr);
  assign empty = (w_ptr == r_ptr);
endmodule

fifo/fifo_tb.v
`include "fifo.v"

module fifo_tb;

  // Parameters
  parameter DEPTH = 8;
  parameter DATA_WIDTH = 8;

  // Inputs
  reg clk;
  reg rst_n;
  reg w_en;
  reg r_en;
  reg [DATA_WIDTH-1:0] data_in;

  // Outputs
  wire [DATA_WIDTH-1:0] data_out;
  wire full;
  wire empty;

  // Instantiate the FIFO module
  fifo #(
    .DEPTH(DEPTH),
    .DATA_WIDTH(DATA_WIDTH)
  ) dut (
    .clk(clk),
    .rst_n(rst_n),
    .w_en(w_en),
    .r_en(r_en),
    .data_in(data_in),
    .data_out(data_out),
    .full(full),
    .empty(empty)
  );

  // Clock generation
  always begin
    clk = 0;
    #5;
    clk = 1;
    #5;
  end

  // Reset generation
  initial begin
    rst_n = 0;
    #10;
    rst_n = 1;
  end

  // Write test
  initial begin
    // Wait for the FIFO to empty
    repeat (10) @(posedge clk);

    // Write some data to the FIFO
    for (int i = 0; i < DEPTH-1; i++) begin
      w_en = 1;
      data_in = i;
      @(posedge clk);
      $display("WRITTEN: %d, FULL: %0d, EMPTY: %0d", i, full, empty);
    end


    // Wait for a while
    repeat (10) @(posedge clk);

    // Disable write enable
    w_en = 0;

    // Wait for a while
    repeat (10) @(posedge clk);

    // Read some data from the FIFO
    for (int i = 0; i < DEPTH-1; i++) begin
        r_en = 1;
        @(posedge clk);
        $display("READING: %d, FULL: %0d, EMPTY: %0d", data_out, full, empty);
        if (data_out !== i) begin
            $error("Data mismatch: expected %d, actual %d", i, data_out);
        end
    end

    // Try to read more data (FIFO should be empty)
    r_en = 1;
    @(posedge clk);

    // Wait for a while
    repeat (10) @(posedge clk);

    // Disable read enable
    r_en = 0;

    // Wait for a while
    repeat (10) @(posedge clk);

    $finish;

  end

endmodule

fifo/waves.vcd
$date
	Sat May  6 21:57:03 2023
$end

$version
	Synopsys VCS version R-2020.12
$end

$timescale
	1s
$end

$comment Csum: 1 c78ecf22ac247da9 $end


$scope module fifo_tb $end
$var reg 1 ! clk $end
$var reg 1 " rst_n $end
$var reg 1 # w_en $end
$var reg 1 $ r_en $end
$var reg 8 % data_in [7:0] $end
$var wire 8 & data_out [7:0] $end
$var wire 1 ' full $end
$var wire 1 ( empty $end

$scope begin unnamed$$_0 $end
$upscope $end


$scope begin unnamed$$_1 $end
$upscope $end


$scope module dut $end
$var wire 1 ! clk $end
$var wire 1 " rst_n $end
$var wire 1 # w_en $end
$var wire 1 $ r_en $end
$var wire 8 % data_in [7:0] $end
$var reg 8 & data_out [7:0] $end
$var wire 1 ' full $end
$var wire 1 ( empty $end
$var reg 3 ) w_ptr [2:0] $end
$var reg 3 * r_ptr [2:0] $end
$upscope $end

$upscope $end

$enddefinitions $end

#0
$dumpvars
0!
x(
x'
x$
0"
x#
bxxxxxxxx %
bxxxxxxxx &
bxxx *
bxxx )
$end
#5
1!
b000 )
0'
1(
b000 *
b00000000 &
#10
1"
0!
#15
1!
#20
0!
#25
1!
#30
0!
#35
1!
#40
0!
#45
1!
#50
0!
#55
1!
#60
0!
#65
1!
#70
0!
#75
1!
#80
0!
#85
1!
#90
0!
#95
1!
1#
b00000000 %
b001 )
0(
#100
0!
#105
1!
b00000001 %
b010 )
#110
0!
#115
1!
b00000010 %
b011 )
#120
0!
#125
1!
b00000011 %
b100 )
#130
0!
#135
1!
b00000100 %
b101 )
#140
0!
#145
1!
b00000101 %
b110 )
#150
0!
#155
1!
b00000110 %
b111 )
1'
#160
0!
#165
1!
#170
0!
#175
1!
#180
0!
#185
1!
#190
0!
#195
1!
#200
0!
#205
1!
#210
0!
#215
1!
#220
0!
#225
1!
#230
0!
#235
1!
#240
0!
#245
1!
#250
0!
#255
1!
#260
0!
#265
1!
0#
#270
0!
#275
1!
#280
0!
#285
1!
#290
0!
#295
1!
#300
0!
#305
1!
#310
0!
#315
1!
#320
0!
#325
1!
#330
0!
#335
1!
#340
0!
#345
1!
#350
0!
#355
1!
#360
0!
#365
1!
1$
b001 *
0'
#370
0!
#375
1!
b00000001 &
b010 *
#380
0!
#385
1!
b00000010 &
b011 *
#390
0!
#395
1!
b00000011 &
b100 *
#400
0!
#405
1!
b00000100 &
b101 *
#410
0!
#415
1!
b00000101 &
b110 *
#420
0!
#425
1!
b00000110 &
b111 *
1(
#430
0!
#435
1!
#440
0!
#445
1!
#450
0!
#455
1!
#460
0!
#465
1!
#470
0!
#475
1!
#480
0!
#485
1!
#490
0!
#495
1!
#500
0!
#505
1!
#510
0!
#515
1!
#520
0!
#525
1!
#530
0!
#535
1!
#540
0!
#545
1!
0$
